{
  "words": [
    {
      "id": 1,
      "image": "heart.jpeg",
      "word": "Heart",
      "listLetters": ["H", "t", "e", "f", "r", "d", "a", "y", "u", "B"]
    },
    {
      "id": 2,
      "image": "brain.jpeg",
      "word": "Brain",
      "listLetters": ["n", "f", "B", "i", "r", "d", "r", "a", "a", "y"]
    },
    {
      "id": 3,
      "image": "liver.png",
      "word": "Liver",
      "listLetters": ["e", "i", "f", "L", "v", "B", "r", "i", "r", "d"]
    },
    {
      "id": 4,
      "image": "blood.png",
      "word": "Blood",
      "listLetters": ["B", "d", "l", "o", "i", "r", "o", "B", "r", "d"]
    },
    {
      "id": 5,
      "image": "spleen.jpeg",
      "word": "Spleen",
      "listLetters": ["e", "n", "l", "S", "o", "i", "p", "l", "e", "r"]
    },
    {
      "id": 6,
      "image": "Kidney.jpeg",
      "word": "Kidney",
      "listLetters": ["K", "y", "l", "S", "o", "i", "d", "n", "e", "i"]
    },
    {
      "id": 7,
      "image": "biceps_word.jpeg",
      "word": "Biceps",
      "listLetters": ["B", "p", "c", "o", "i", "r", "o", "e", "r", "s"]
    }
  ]
}
